Metadata-Version: 2.1
Name: maximspiryanovLab3
Version: 1.0
Summary: weather
Author-email: maxim87858@mail.ru
